devops_microsoft_mapping_sspo/__init__.py
devops_microsoft_mapping_sspo/atomic_user_story.py
devops_microsoft_mapping_sspo/base_entity.py
devops_microsoft_mapping_sspo/base_scrum_element.py
devops_microsoft_mapping_sspo/development_team.py
devops_microsoft_mapping_sspo/epic.py
devops_microsoft_mapping_sspo/factories.py
devops_microsoft_mapping_sspo/product_backlog.py
devops_microsoft_mapping_sspo/product_backlog_definition.py
devops_microsoft_mapping_sspo/scrum_atomic_project.py
devops_microsoft_mapping_sspo/scrum_complex_project.py
devops_microsoft_mapping_sspo/scrum_intented_development_task.py
devops_microsoft_mapping_sspo/scrum_performed_development_task.py
devops_microsoft_mapping_sspo/scrum_process.py
devops_microsoft_mapping_sspo/scrum_project.py
devops_microsoft_mapping_sspo/scrum_team.py
devops_microsoft_mapping_sspo/sprint.py
devops_microsoft_mapping_sspo/team_member.py
devops_microsoft_mapping_sspo/user_story.py
devops_microsoft_mapping_sspo-6.1.0.dist-info/METADATA
devops_microsoft_mapping_sspo-6.1.0.dist-info/WHEEL
devops_microsoft_mapping_sspo-6.1.0.dist-info/top_level.txt
devops_microsoft_mapping_sspo-6.1.0.dist-info/RECORD
