Metadata-Version: 2.1
Name: devops-microsoft-mapping-sspo
Version: 6.1.0
Summary: Possui bibliotecas para realizar a integração entre SSPO e Microsoft DevOps
Home-page: UNKNOWN
Author: Paulo Sergio dos Santo Junior
Author-email: paulossjuniort@gmail.com
License: UNKNOWN
Platform: UNKNOWN
Classifier: Programming Language :: Python :: 3
Classifier: License :: OSI Approved :: MIT License
Classifier: Operating System :: OS Independent
Requires-Dist: sspo-db
Requires-Dist: tfsx
